[
    {
        "name": "Devquiz",
        "url": "https://devquiz.site/",
        "urlGithub": "",
        "description": "Sistema de gestion de inventario enfocado en venta de hardware, permite administrar entrada y salida de productos.",
        "skills": ["React", "NodeJS", "JavaScript", "PostgreSQL"]
    },
    {
        "name": "Laser no sekai - Ecommerce",
        "url": "",
        "urlGithub": "",
        "description": "Convierte enlaces largos en enlaces cortos y faciles de compartir.",
        "skills": ["NextJS", "Typescript", "NodeJS", "PostgreSQL"]
    },
    {
        "name": "Api Pokemon Pocket",
        "url": "",
        "urlGithub": "https://github.com/FatuKING/SmallProyectInReact",
        "description": "Monorepositorio de proyectos, cuenta con mas de 10 proyectos distintos.",
        "skills": ["NodeJS", "Typescript", "PostgreSQL"]
    }
]
